flask_api_factory/__init__.py
flask_api_factory/actions/__init__.py
flask_api_factory/actions/amqp.py
flask_api_factory/auth.py
flask_api_factory/constants.py
flask_api_factory/decorators.py
flask_api_factory/filter/__init__.py
flask_api_factory/filter/casts.py
flask_api_factory/openapi/__init__.py
flask_api_factory/openapi/models.py
flask_api_factory/openapi/path.py
flask_api_factory/order.py
flask_api_factory/page.py
flask_api_factory-0.2.3.dist-info/METADATA
flask_api_factory-0.2.3.dist-info/WHEEL
flask_api_factory-0.2.3.dist-info/RECORD
