Metadata-Version: 2.1
Name: flask-api-factory
Version: 0.2.3
Summary: one small flask rest api factory
Home-page: https://github.com/rodrigopmatias/flask-api-factory/blob/main/README.md
Author: Rodrigo Pinheiro Matias
Author-email: rodrigopmatias@gmail.com
Requires-Python: >=3.10,<4.0
Classifier: Programming Language :: Python :: 3
Classifier: Programming Language :: Python :: 3.10
Classifier: Programming Language :: Python :: 3.11
Provides-Extra: mysql
Provides-Extra: postgres
Requires-Dist: flask (>=2.2.2,<3.0.0)
Requires-Dist: flask-migrate (>=4.0.4,<5.0.0)
Requires-Dist: flask-sqlalchemy (>=3.0.3,<4.0.0)
Requires-Dist: gunicorn (>=20.1.0,<21.0.0)
Requires-Dist: mysql (>=0.0.3,<0.0.4) ; extra == "mysql"
Requires-Dist: pika (>=1.3.1,<2.0.0)
Requires-Dist: prometheus-flask-exporter (>=0.21.0,<0.22.0)
Requires-Dist: psycopg2-binary (>=2.9.5,<3.0.0) ; extra == "postgres"
Requires-Dist: pydantic[dotenv] (>=1.10.4,<2.0.0)
Project-URL: Repository, https://github.com/rodrigopmatias/flask-api-factory
